tinycolorpicker
