Metadata-Version: 1.1
Name: django-tinycolorpicker
Version: 0.1.1
Summary: Django Field and Widget implementation of wieringen/tinycolorpicker
Home-page: https://www.github.com/perdixsw/django-tinycolorpicker
Author: Perdix Software
Author-email: ssmith@perdixsw.com
License: MIT
Download-URL: https://www.github.com/perdixsw/django-tinycolorpicker/archive/0.1.1.tar.gz
Keywords: django,color,field,colorpicker,tinycolorpicker
Platform: UNKNOWN
Classifier: Development Status :: 4 - Beta
Classifier: Intended Audience :: Developers
Classifier: License :: OSI Approved :: MIT License
Classifier: Operating System :: OS Independent
Classifier: Programming Language :: Python
Classifier: Programming Language :: Python :: 2.7
Classifier: Programming Language :: Python :: 3
Classifier: Programming Language :: Python :: 3.4
Classifier: Programming Language :: Python :: 3.5
Classifier: Programming Language :: Python :: 3.6
